strtree/__init__.py
strtree/utils.py
strtree-0.2.0.dist-info/LICENSE
strtree-0.2.0.dist-info/METADATA
strtree-0.2.0.dist-info/WHEEL
strtree-0.2.0.dist-info/top_level.txt
strtree-0.2.0.dist-info/RECORD
