Metadata-Version: 2.1
Name: strtree
Version: 0.2.0
Summary: Python package for strings binary classification, based on regular expressions put in a decision tree.
Author-email: Anton Saroka <anton.soroka.1313@gmail.com>
Project-URL: Homepage, https://github.com/AntonSarr/strtree
Project-URL: Issues, https://github.com/AntonSarr/strtree/issues
Classifier: Programming Language :: Python :: 3
Classifier: License :: OSI Approved :: MIT License
Classifier: Operating System :: OS Independent
Requires-Python: >=3.8
License-File: LICENSE
